pysv/CMakeLists.txt
pysv/__init__.py
pysv/codegen.py
pysv/compile.py
pysv/frame.py
pysv/function.py
pysv/model.py
pysv/pyast.py
pysv/types.py
pysv/util.py
pysv/extern/pybind11/CMakeLists.txt
pysv/extern/pybind11/MANIFEST.in
pysv/extern/pybind11/docs/requirements.txt
pysv/extern/pybind11/include/pybind11/attr.h
pysv/extern/pybind11/include/pybind11/buffer_info.h
pysv/extern/pybind11/include/pybind11/cast.h
pysv/extern/pybind11/include/pybind11/chrono.h
pysv/extern/pybind11/include/pybind11/common.h
pysv/extern/pybind11/include/pybind11/complex.h
pysv/extern/pybind11/include/pybind11/eigen.h
pysv/extern/pybind11/include/pybind11/embed.h
pysv/extern/pybind11/include/pybind11/eval.h
pysv/extern/pybind11/include/pybind11/functional.h
pysv/extern/pybind11/include/pybind11/gil.h
pysv/extern/pybind11/include/pybind11/iostream.h
pysv/extern/pybind11/include/pybind11/numpy.h
pysv/extern/pybind11/include/pybind11/operators.h
pysv/extern/pybind11/include/pybind11/options.h
pysv/extern/pybind11/include/pybind11/pybind11.h
pysv/extern/pybind11/include/pybind11/pytypes.h
pysv/extern/pybind11/include/pybind11/stl.h
pysv/extern/pybind11/include/pybind11/stl_bind.h
pysv/extern/pybind11/include/pybind11/type_caster_pyobject_ptr.h
pysv/extern/pybind11/include/pybind11/detail/class.h
pysv/extern/pybind11/include/pybind11/detail/common.h
pysv/extern/pybind11/include/pybind11/detail/descr.h
pysv/extern/pybind11/include/pybind11/detail/init.h
pysv/extern/pybind11/include/pybind11/detail/internals.h
pysv/extern/pybind11/include/pybind11/detail/type_caster_base.h
pysv/extern/pybind11/include/pybind11/detail/typeid.h
pysv/extern/pybind11/include/pybind11/eigen/common.h
pysv/extern/pybind11/include/pybind11/eigen/matrix.h
pysv/extern/pybind11/include/pybind11/eigen/tensor.h
pysv/extern/pybind11/include/pybind11/stl/filesystem.h
pysv/extern/pybind11/tools/FindCatch.cmake
pysv/extern/pybind11/tools/FindEigen3.cmake
pysv/extern/pybind11/tools/FindPythonLibsNew.cmake
pysv-0.3.1.dist-info/LICENSE
pysv-0.3.1.dist-info/METADATA
pysv-0.3.1.dist-info/WHEEL
pysv-0.3.1.dist-info/top_level.txt
pysv-0.3.1.dist-info/RECORD
