Metadata-Version: 2.1
Name: pysv
Version: 0.3.1
Summary: UNKNOWN
Home-page: https://github.com/Kuree/pysv
Author: Keyi Zhang
Author-email: keyi@cs.stanford.edu
License: UNKNOWN
Platform: UNKNOWN
Requires-Python: >=3.6
Requires-Dist: astor
Provides-Extra: test
Requires-Dist: numpy ; extra == 'test'
Requires-Dist: pytest ; extra == 'test'
Provides-Extra: test-full
Requires-Dist: tensorflow-cpu ; extra == 'test-full'
Requires-Dist: pytest ; extra == 'test-full'
